openbb_oilpriceapi/__init__.py
openbb_oilpriceapi/models/__init__.py
openbb_oilpriceapi/models/oil_historical.py
openbb_oilpriceapi/models/oil_price.py
openbb_oilpriceapi/utils/__init__.py
openbb_oilpriceapi/utils/constants.py
openbb_oilpriceapi-0.1.0.dist-info/METADATA
openbb_oilpriceapi-0.1.0.dist-info/WHEEL
openbb_oilpriceapi-0.1.0.dist-info/entry_points.txt
openbb_oilpriceapi-0.1.0.dist-info/licenses/LICENSE
openbb_oilpriceapi-0.1.0.dist-info/RECORD
