Metadata-Version: 2.4
Name: openbb-oilpriceapi
Version: 0.1.0
Summary: OpenBB provider for OilPriceAPI - Real-time oil and commodity prices (WTI, Brent, Urals, Natural Gas, Coal)
License: MIT
License-File: LICENSE
Keywords: openbb,oil,commodity,api,energy,prices,wti,brent,urals
Author: OilPriceAPI
Author-email: support@oilpriceapi.com
Requires-Python: >=3.10,<3.14
Classifier: License :: OSI Approved :: MIT License
Classifier: Programming Language :: Python :: 3
Classifier: Programming Language :: Python :: 3.10
Classifier: Programming Language :: Python :: 3.11
Classifier: Programming Language :: Python :: 3.12
Classifier: Programming Language :: Python :: 3.13
Requires-Dist: httpx (>=0.27.0,<0.28.0)
Requires-Dist: openbb-core (>=1.5.1,<2.0.0)
Requires-Dist: tenacity (>=8.2.0,<9.0.0)
Project-URL: Repository, https://github.com/OilpriceAPI/openbb-oilpriceapi
